maexpa/__init__.py
maexpa/__main__.py
maexpa/exception.py
maexpa/expression.py
maexpa/tokens.py
maexpa-0.1.dist-info/LICENSE
maexpa-0.1.dist-info/METADATA
maexpa-0.1.dist-info/WHEEL
maexpa-0.1.dist-info/top_level.txt
maexpa-0.1.dist-info/RECORD
