Metadata-Version: 2.1
Name: maexpa
Version: 0.1
Summary: Extensible mathematical expression analyzer with callbacks for variables and functions
Home-page: https://github.com/aemsenhuber/maexpa
Author: Alexandre Emsenhuber
Author-email: emsenhuber@lpl.arizona.edu
License: UNKNOWN
Platform: UNKNOWN
Classifier: Programming Language :: Python :: 3
Classifier: License :: OSI Approved :: Apache Software License
Classifier: Operating System :: OS Independent
